django_fingerprint_rt-0.2.0.dist-info/METADATA
django_fingerprint_rt-0.2.0.dist-info/WHEEL
django_fingerprint_rt-0.2.0.dist-info/entry_points.txt
django_fingerprint_rt-0.2.0.dist-info/licenses/LICENSE
fingerprint/__init__.py
fingerprint/_internal/__init__.py
fingerprint/admin.py
fingerprint/migrations/0001_initial.py
fingerprint/migrations/0002_url_browserfingerprint_fingerprint_url_id_9faee4_idx_and_more.py
fingerprint/migrations/0003_alter_browserfingerprint_url_and_more.py
fingerprint/migrations/0004_requestfingerprint_referer_country.py
fingerprint/migrations/0005_user_session_utm_fields.py
fingerprint/migrations/0006_usersession_referer.py
fingerprint/migrations/__init__.py
fingerprint/models.py
fingerprint/static/FingerprintJSv3.4.0.js
fingerprint/templates/fingerprint/fingerprint.html
fingerprint/templates/fingerprint/include/script.html
fingerprint/templatetags/__init__.py
fingerprint/templatetags/hit_count.py
fingerprint/v1/__init__.py
fingerprint/views.py
django_fingerprint_rt-0.2.0.dist-info/RECORD
