Metadata-Version: 2.1
Name: django-fingerprint-rt
Version: 0.2.0
Summary: Users fingerprinting for your django app
Author-Email: Reef Technologies <opensource@reef.pl>, Aleksandr Goncharov <aleksandr.goncharov@reef.pl>
License: MIT
Classifier: Framework :: Django
Classifier: Framework :: Django :: 4.2
Classifier: Operating System :: OS Independent
Classifier: Topic :: Software Development :: Libraries
Classifier: License :: OSI Approved :: MIT License
Classifier: Programming Language :: Python :: 3
Classifier: Programming Language :: Python :: 3.9
Classifier: Programming Language :: Python :: 3.11
Classifier: Programming Language :: Python :: 3.12
Project-URL: Source, https://github.com/reef-technologies/django-fingerprint-rt
Project-URL: Issue Tracker, https://github.com/reef-technologies/django-fingerprint-rt/issues
Requires-Python: >=3.9
Requires-Dist: django-ipware~=6.0.4
Requires-Dist: django>=3.1
Provides-Extra: cache
Requires-Dist: django-cacheops>=7.0.2; extra == "cache"
